A3/day4/bram_example.v
`timescale 1ns / 1ps

// Block RAM (Read-First mode) example code 
// For more information, please refer to Xilinx UG473 and UG687
// UG473: https://japan.xilinx.com/support/documentation/user_guides/j_ug473_7Series_Memory_Resources.pdf
// UG687: https://japan.xilinx.com/support/documentation/sw_manuals_j/xilinx14_7/xst_v6s6.pdf

module bram_example ( 
    input wire  clk, we,
    input wire [7:0] addr,
    input wire [3:0] w_data,
    output wire [3:0] r_data
);

    reg [3:0] mem [0:255];
    reg [3:0] mem_out;

    // ここは initial begin を使わないで
    initial begin
        $readmemh("mem.hex", mem);
    end
    
    always @(posedge clk) begin
        if (we) mem[addr] <= w_data;  // synchronous write
        mem_out <= mem[addr];  // synchronous read
    end
    
    assign r_data = mem_out;

endmodule

A3/day4/task1_mod.v
module task1_mod(
  input wire clk,
  output wire [3:0] out
);

  reg we;
  reg [7:0] addr = 0;
  wire [3:0] w_data, r_data;

  bram_example bram_mod(clk, we, addr, w_data, r_data);

  integer index = 0;
  always @(posedge clk) begin
    index = index + 1;
    addr <= index;
    if (index >= 256)
      index = 0;
  end

  assign out = r_data;

endmodule

A3/day4/task1_sim.v
module task1_sim;

    parameter CYCLE = 10;
    parameter HALF_CYCLE = CYCLE / 2;

    reg clk;
    wire [3:0] out;

    task1_mod task1(clk, out);

    initial begin
      $dumpfile("task1_sim.vcd");
      $dumpvars(0, task1);

      for (integer i = 0; i < 256; i = i + 1) begin
        clk = 1'b1;
        #HALF_CYCLE;
        $display("mem[%d]: %h", i, out);
        #HALF_CYCLE;
        clk = 1'b0;
        #CYCLE;
      end

      $finish;
    end

endmodule

A3/day4/task1_sim.vcd
$date
	Tue Apr 23 16:24:21 2024
$end
$version
	Icarus Verilog
$end
$timescale
	1ps
$end
$scope module task1_sim $end
$scope module task1 $end
$var wire 1 ! clk $end
$var wire 4 " out [3:0] $end
$var wire 4 # w_data [3:0] $end
$var wire 4 $ r_data [3:0] $end
$var reg 8 % addr [7:0] $end
$var reg 1 & we $end
$var integer 32 ' index [31:0] $end
$scope module bram_mod $end
$var wire 8 ( addr [7:0] $end
$var wire 1 ! clk $end
$var wire 4 ) r_data [3:0] $end
$var wire 4 * w_data [3:0] $end
$var wire 1 & we $end
$var reg 4 + mem_out [3:0] $end
$upscope $end
$upscope $end
$upscope $end
$enddefinitions $end
#0
$dumpvars
b110 +
bz *
b110 )
b1 (
b1 '
x&
b1 %
b110 $
bz #
b110 "
1!
$end
#10000000000000
0!
#20000000000000
b10 %
b10 (
b1100 "
b1100 $
b1100 )
b1100 +
b10 '
1!
#30000000000000
0!
#40000000000000
b1111 "
b1111 $
b1111 )
b1111 +
b11 %
b11 (
b11 '
1!
#50000000000000
0!
#60000000000000
b100 %
b100 (
b1010 "
b1010 $
b1010 )
b1010 +
b100 '
1!
#70000000000000
0!
#80000000000000
b1011 "
b1011 $
b1011 )
b1011 +
b101 %
b101 (
b101 '
1!
#90000000000000
0!
#100000000000000
b110 %
b110 (
b1100 "
b1100 $
b1100 )
b1100 +
b110 '
1!
#110000000000000
0!
#120000000000000
b11 "
b11 $
b11 )
b11 +
b111 %
b111 (
b111 '
1!
#130000000000000
0!
#140000000000000
b1000 %
b1000 (
b1001 "
b1001 $
b1001 )
b1001 +
b1000 '
1!
#150000000000000
0!
#160000000000000
b1 "
b1 $
b1 )
b1 +
b1001 %
b1001 (
b1001 '
1!
#170000000000000
0!
#180000000000000
b1010 %
b1010 (
b1010 "
b1010 $
b1010 )
b1010 +
b1010 '
1!
#190000000000000
0!
#200000000000000
b1110 "
b1110 $
b1110 )
b1110 +
b1011 %
b1011 (
b1011 '
1!
#210000000000000
0!
#220000000000000
b1100 %
b1100 (
b1 "
b1 $
b1 )
b1 +
b1100 '
1!
#230000000000000
0!
#240000000000000
b1000 "
b1000 $
b1000 )
b1000 +
b1101 %
b1101 (
b1101 '
1!
#250000000000000
0!
#260000000000000
b1110 %
b1110 (
b1110 "
b1110 $
b1110 )
b1110 +
b1110 '
1!
#270000000000000
0!
#280000000000000
b1111 %
b1111 (
b1111 '
1!
#290000000000000
0!
#300000000000000
b10000 %
b10000 (
b10000 '
1!
#310000000000000
0!
#320000000000000
b11 "
b11 $
b11 )
b11 +
b10001 %
b10001 (
b10001 '
1!
#330000000000000
0!
#340000000000000
b10010 %
b10010 (
b110 "
b110 $
b110 )
b110 +
b10010 '
1!
#350000000000000
0!
#360000000000000
b10 "
b10 $
b10 )
b10 +
b10011 %
b10011 (
b10011 '
1!
#370000000000000
0!
#380000000000000
b10100 %
b10100 (
b100 "
b100 $
b100 )
b100 +
b10100 '
1!
#390000000000000
0!
#400000000000000
b1111 "
b1111 $
b1111 )
b1111 +
b10101 %
b10101 (
b10101 '
1!
#410000000000000
0!
#420000000000000
b10110 %
b10110 (
b100 "
b100 $
b100 )
b100 +
b10110 '
1!
#430000000000000
0!
#440000000000000
b1 "
b1 $
b1 )
b1 +
b10111 %
b10111 (
b10111 '
1!
#450000000000000
0!
#460000000000000
b11000 %
b11000 (
b10 "
b10 $
b10 )
b10 +
b11000 '
1!
#470000000000000
0!
#480000000000000
b11001 %
b11001 (
b11001 '
1!
#490000000000000
0!
#500000000000000
b11010 %
b11010 (
b1010 "
b1010 $
b1010 )
b1010 +
b11010 '
1!
#510000000000000
0!
#520000000000000
b11 "
b11 $
b11 )
b11 +
b11011 %
b11011 (
b11011 '
1!
#530000000000000
0!
#540000000000000
b11100 %
b11100 (
b1010 "
b1010 $
b1010 )
b1010 +
b11100 '
1!
#550000000000000
0!
#560000000000000
b11101 %
b11101 (
b11101 '
1!
#570000000000000
0!
#580000000000000
b11110 %
b11110 (
b1001 "
b1001 $
b1001 )
b1001 +
b11110 '
1!
#590000000000000
0!
#600000000000000
b110 "
b110 $
b110 )
b110 +
b11111 %
b11111 (
b11111 '
1!
#610000000000000
0!
#620000000000000
b100000 %
b100000 (
b11 "
b11 $
b11 )
b11 +
b100000 '
1!
#630000000000000
0!
#640000000000000
b1101 "
b1101 $
b1101 )
b1101 +
b100001 %
b100001 (
b100001 '
1!
#650000000000000
0!
#660000000000000
b100010 %
b100010 (
b1011 "
b1011 $
b1011 )
b1011 +
b100010 '
1!
#670000000000000
0!
#680000000000000
b100011 %
b100011 (
b100011 '
1!
#690000000000000
0!
#700000000000000
b100100 %
b100100 (
b1 "
b1 $
b1 )
b1 +
b100100 '
1!
#710000000000000
0!
#720000000000000
b111 "
b111 $
b111 )
b111 +
b100101 %
b100101 (
b100101 '
1!
#730000000000000
0!
#740000000000000
b100110 %
b100110 (
b1 "
b1 $
b1 )
b1 +
b100110 '
1!
#750000000000000
0!
#760000000000000
b1010 "
b1010 $
b1010 )
b1010 +
b100111 %
b100111 (
b100111 '
1!
#770000000000000
0!
#780000000000000
b101000 %
b101000 (
b1011 "
b1011 $
b1011 )
b1011 +
b101000 '
1!
#790000000000000
0!
#800000000000000
b101 "
b101 $
b101 )
b101 +
b101001 %
b101001 (
b101001 '
1!
#810000000000000
0!
#820000000000000
b101010 %
b101010 (
b1110 "
b1110 $
b1110 )
b1110 +
b101010 '
1!
#830000000000000
0!
#840000000000000
b1 "
b1 $
b1 )
b1 +
b101011 %
b101011 (
b101011 '
1!
#850000000000000
0!
#860000000000000
b101100 %
b101100 (
b1100 "
b1100 $
b1100 )
b1100 +
b101100 '
1!
#870000000000000
0!
#880000000000000
b1010 "
b1010 $
b1010 )
b1010 +
b101101 %
b101101 (
b101101 '
1!
#890000000000000
0!
#900000000000000
b101110 %
b101110 (
b111 "
b111 $
b111 )
b111 +
b101110 '
1!
#910000000000000
0!
#920000000000000
b101111 %
b101111 (
b101111 '
1!
#930000000000000
0!
#940000000000000
b110000 %
b110000 (
b1000 "
b1000 $
b1000 )
b1000 +
b110000 '
1!
#950000000000000
0!
#960000000000000
b1010 "
b1010 $
b1010 )
b1010 +
b110001 %
b110001 (
b110001 '
1!
#970000000000000
0!
#980000000000000
b110010 %
b110010 (
b1110 "
b1110 $
b1110 )
b1110 +
b110010 '
1!
#990000000000000
0!
#1000000000000000
b110011 %
b110011 (
b110011 '
1!
#1010000000000000
0!
#1020000000000000
b110100 %
b110100 (
b1111 "
b1111 $
b1111 )
b1111 +
b110100 '
1!
#1030000000000000
0!
#1040000000000000
b1 "
b1 $
b1 )
b1 +
b110101 %
b110101 (
b110101 '
1!
#1050000000000000
0!
#1060000000000000
b110110 %
b110110 (
b11 "
b11 $
b11 )
b11 +
b110110 '
1!
#1070000000000000
0!
#1080000000000000
b1000 "
b1000 $
b1000 )
b1000 +
b110111 %
b110111 (
b110111 '
1!
#1090000000000000
0!
#1100000000000000
b111000 %
b111000 (
b10 "
b10 $
b10 )
b10 +
b111000 '
1!
#1110000000000000
0!
#1120000000000000
b1100 "
b1100 $
b1100 )
b1100 +
b111001 %
b111001 (
b111001 '
1!
#1130000000000000
0!
#1140000000000000
b111010 %
b111010 (
b1111 "
b1111 $
b1111 )
b1111 +
b111010 '
1!
#1150000000000000
0!
#1160000000000000
b111 "
b111 $
b111 )
b111 +
b111011 %
b111011 (
b111011 '
1!
#1170000000000000
0!
#1180000000000000
b111100 %
b111100 (
b1 "
b1 $
b1 )
b1 +
b111100 '
1!
#1190000000000000
0!
#1200000000000000
b1010 "
b1010 $
b1010 )
b1010 +
b111101 %
b111101 (
b111101 '
1!
#1210000000000000
0!
#1220000000000000
b111110 %
b111110 (
b1100 "
b1100 $
b1100 )
b1100 +
b111110 '
1!
#1230000000000000
0!
#1240000000000000
b111 "
b111 $
b111 )
b111 +
b111111 %
b111111 (
b111111 '
1!
#1250000000000000
0!
#1260000000000000
b1000000 %
b1000000 (
b1 "
b1 $
b1 )
b1 +
b1000000 '
1!
#1270000000000000
0!
#1280000000000000
b110 "
b110 $
b110 )
b110 +
b1000001 %
b1000001 (
b1000001 '
1!
#1290000000000000
0!
#1300000000000000
b1000010 %
b1000010 (
b1100 "
b1100 $
b1100 )
b1100 +
b1000010 '
1!
#1310000000000000
0!
#1320000000000000
b1111 "
b1111 $
b1111 )
b1111 +
b1000011 %
b1000011 (
b1000011 '
1!
#1330000000000000
0!
#1340000000000000
b1000100 %
b1000100 (
b111 "
b111 $
b111 )
b111 +
b1000100 '
1!
#1350000000000000
0!
#1360000000000000
b1 "
b1 $
b1 )
b1 +
b1000101 %
b1000101 (
b1000101 '
1!
#1370000000000000
0!
#1380000000000000
b1000110 %
b1000110 (
b1111 "
b1111 $
b1111 )
b1111 +
b1000110 '
1!
#1390000000000000
0!
#1400000000000000
b1101 "
b1101 $
b1101 )
b1101 +
b1000111 %
b1000111 (
b1000111 '
1!
#1410000000000000
0!
#1420000000000000
b1001000 %
b1001000 (
b1011 "
b1011 $
b1011 )
b1011 +
b1001000 '
1!
#1430000000000000
0!
#1440000000000000
b1111 "
b1111 $
b1111 )
b1111 +
b1001001 %
b1001001 (
b1001001 '
1!
#1450000000000000
0!
#1460000000000000
b1001010 %
b1001010 (
b1001010 '
1!
#1470000000000000
0!
#1480000000000000
b100 "
b100 $
b100 )
b100 +
b1001011 %
b1001011 (
b1001011 '
1!
#1490000000000000
0!
#1500000000000000
b1001100 %
b1001100 (
b0 "
b0 $
b0 )
b0 +
b1001100 '
1!
#1510000000000000
0!
#1520000000000000
b1111 "
b1111 $
b1111 )
b1111 +
b1001101 %
b1001101 (
b1001101 '
1!
#1530000000000000
0!
#1540000000000000
b1001110 %
b1001110 (
b1001110 '
1!
#1550000000000000
0!
#1560000000000000
b100 "
b100 $
b100 )
b100 +
b1001111 %
b1001111 (
b1001111 '
1!
#1570000000000000
0!
#1580000000000000
b1010000 %
b1010000 (
b101 "
b101 $
b101 )
b101 +
b1010000 '
1!
#1590000000000000
0!
#1600000000000000
b1010 "
b1010 $
b1010 )
b1010 +
b1010001 %
b1010001 (
b1010001 '
1!
#1610000000000000
0!
#1620000000000000
b1010010 %
b1010010 (
b10 "
b10 $
b10 )
b10 +
b1010010 '
1!
#1630000000000000
0!
#1640000000000000
b1011 "
b1011 $
b1011 )
b1011 +
b1010011 %
b1010011 (
b1010011 '
1!
#1650000000000000
0!
#1660000000000000
b1010100 %
b1010100 (
b1001 "
b1001 $
b1001 )
b1001 +
b1010100 '
1!
#1670000000000000
0!
#1680000000000000
b100 "
b100 $
b100 )
b100 +
b1010101 %
b1010101 (
b1010101 '
1!
#1690000000000000
0!
#1700000000000000
b1010110 %
b1010110 (
b1111 "
b1111 $
b1111 )
b1111 +
b1010110 '
1!
#1710000000000000
0!
#1720000000000000
b11 "
b11 $
b11 )
b11 +
b1010111 %
b1010111 (
b1010111 '
1!
#1730000000000000
0!
#1740000000000000
b1011000 %
b1011000 (
b111 "
b111 $
b111 )
b111 +
b1011000 '
1!
#1750000000000000
0!
#1760000000000000
b11 "
b11 $
b11 )
b11 +
b1011001 %
b1011001 (
b1011001 '
1!
#1770000000000000
0!
#1780000000000000
b1011010 %
b1011010 (
b1110 "
b1110 $
b1110 )
b1110 +
b1011010 '
1!
#1790000000000000
0!
#1800000000000000
b101 "
b101 $
b101 )
b101 +
b1011011 %
b1011011 (
b1011011 '
1!
#1810000000000000
0!
#1820000000000000
b1011100 %
b1011100 (
b111 "
b111 $
b111 )
b111 +
b1011100 '
1!
#1830000000000000
0!
#1840000000000000
b1100 "
b1100 $
b1100 )
b1100 +
b1011101 %
b1011101 (
b1011101 '
1!
#1850000000000000
0!
#1860000000000000
b1011110 %
b1011110 (
b1111 "
b1111 $
b1111 )
b1111 +
b1011110 '
1!
#1870000000000000
0!
#1880000000000000
b100 "
b100 $
b100 )
b100 +
b1011111 %
b1011111 (
b1011111 '
1!
#1890000000000000
0!
#1900000000000000
b1100000 %
b1100000 (
b1 "
b1 $
b1 )
b1 +
b1100000 '
1!
#1910000000000000
0!
#1920000000000000
b1001 "
b1001 $
b1001 )
b1001 +
b1100001 %
b1100001 (
b1100001 '
1!
#1930000000000000
0!
#1940000000000000
b1100010 %
b1100010 (
b1111 "
b1111 $
b1111 )
b1111 +
b1100010 '
1!
#1950000000000000
0!
#1960000000000000
b111 "
b111 $
b111 )
b111 +
b1100011 %
b1100011 (
b1100011 '
1!
#1970000000000000
0!
#1980000000000000
b1100100 %
b1100100 (
b1110 "
b1110 $
b1110 )
b1110 +
b1100100 '
1!
#1990000000000000
0!
#2000000000000000
b1010 "
b1010 $
b1010 )
b1010 +
b1100101 %
b1100101 (
b1100101 '
1!
#2010000000000000
0!
#2020000000000000
b1100110 %
b1100110 (
b1001 "
b1001 $
b1001 )
b1001 +
b1100110 '
1!
#2030000000000000
0!
#2040000000000000
b0 "
b0 $
b0 )
b0 +
b1100111 %
b1100111 (
b1100111 '
1!
#2050000000000000
0!
#2060000000000000
b1101000 %
b1101000 (
b111 "
b111 $
b111 )
b111 +
b1101000 '
1!
#2070000000000000
0!
#2080000000000000
b101 "
b101 $
b101 )
b101 +
b1101001 %
b1101001 (
b1101001 '
1!
#2090000000000000
0!
#2100000000000000
b1101010 %
b1101010 (
b11 "
b11 $
b11 )
b11 +
b1101010 '
1!
#2110000000000000
0!
#2120000000000000
b1100 "
b1100 $
b1100 )
b1100 +
b1101011 %
b1101011 (
b1101011 '
1!
#2130000000000000
0!
#2140000000000000
b1101100 %
b1101100 (
b0 "
b0 $
b0 )
b0 +
b1101100 '
1!
#2150000000000000
0!
#2160000000000000
b10 "
b10 $
b10 )
b10 +
b1101101 %
b1101101 (
b1101101 '
1!
#2170000000000000
0!
#2180000000000000
b1101110 %
b1101110 (
b1001 "
b1001 $
b1001 )
b1001 +
b1101110 '
1!
#2190000000000000
0!
#2200000000000000
b1111 "
b1111 $
b1111 )
b1111 +
b1101111 %
b1101111 (
b1101111 '
1!
#2210000000000000
0!
#2220000000000000
b1110000 %
b1110000 (
b1011 "
b1011 $
b1011 )
b1011 +
b1110000 '
1!
#2230000000000000
0!
#2240000000000000
b11 "
b11 $
b11 )
b11 +
b1110001 %
b1110001 (
b1110001 '
1!
#2250000000000000
0!
#2260000000000000
b1110010 %
b1110010 (
b1101 "
b1101 $
b1101 )
b1101 +
b1110010 '
1!
#2270000000000000
0!
#2280000000000000
b100 "
b100 $
b100 )
b100 +
b1110011 %
b1110011 (
b1110011 '
1!
#2290000000000000
0!
#2300000000000000
b1110100 %
b1110100 (
b1110 "
b1110 $
b1110 )
b1110 +
b1110100 '
1!
#2310000000000000
0!
#2320000000000000
b1110101 %
b1110101 (
b1110101 '
1!
#2330000000000000
0!
#2340000000000000
b1110110 %
b1110110 (
b1100 "
b1100 $
b1100 )
b1100 +
b1110110 '
1!
#2350000000000000
0!
#2360000000000000
b1001 "
b1001 $
b1001 )
b1001 +
b1110111 %
b1110111 (
b1110111 '
1!
#2370000000000000
0!
#2380000000000000
b1111000 %
b1111000 (
b1000 "
b1000 $
b1000 )
b1000 +
b1111000 '
1!
#2390000000000000
0!
#2400000000000000
b1101 "
b1101 $
b1101 )
b1101 +
b1111001 %
b1111001 (
b1111001 '
1!
#2410000000000000
0!
#2420000000000000
b1111010 %
b1111010 (
b1001 "
b1001 $
b1001 )
b1001 +
b1111010 '
1!
#2430000000000000
0!
#2440000000000000
b111 "
b111 $
b111 )
b111 +
b1111011 %
b1111011 (
b1111011 '
1!
#2450000000000000
0!
#2460000000000000
b1111100 %
b1111100 (
b11 "
b11 $
b11 )
b11 +
b1111100 '
1!
#2470000000000000
0!
#2480000000000000
b101 "
b101 $
b101 )
b101 +
b1111101 %
b1111101 (
b1111101 '
1!
#2490000000000000
0!
#2500000000000000
b1111110 %
b1111110 (
b1111110 '
1!
#2510000000000000
0!
#2520000000000000
b1111 "
b1111 $
b1111 )
b1111 +
b1111111 %
b1111111 (
b1111111 '
1!
#2530000000000000
0!
#2540000000000000
b10000000 %
b10000000 (
b10 "
b10 $
b10 )
b10 +
b10000000 '
1!
#2550000000000000
0!
#2560000000000000
b1100 "
b1100 $
b1100 )
b1100 +
b10000001 %
b10000001 (
b10000001 '
1!
#2570000000000000
0!
#2580000000000000
b10000010 %
b10000010 (
b100 "
b100 $
b100 )
b100 +
b10000010 '
1!
#2590000000000000
0!
#2600000000000000
b10000011 %
b10000011 (
b10000011 '
1!
#2610000000000000
0!
#2620000000000000
b10000100 %
b10000100 (
b1000 "
b1000 $
b1000 )
b1000 +
b10000100 '
1!
#2630000000000000
0!
#2640000000000000
b1111 "
b1111 $
b1111 )
b1111 +
b10000101 %
b10000101 (
b10000101 '
1!
#2650000000000000
0!
#2660000000000000
b10000110 %
b10000110 (
b10 "
b10 $
b10 )
b10 +
b10000110 '
1!
#2670000000000000
0!
#2680000000000000
b110 "
b110 $
b110 )
b110 +
b10000111 %
b10000111 (
b10000111 '
1!
#2690000000000000
0!
#2700000000000000
b10001000 %
b10001000 (
b1101 "
b1101 $
b1101 )
b1101 +
b10001000 '
1!
#2710000000000000
0!
#2720000000000000
b11 "
b11 $
b11 )
b11 +
b10001001 %
b10001001 (
b10001001 '
1!
#2730000000000000
0!
#2740000000000000
b10001010 %
b10001010 (
b10 "
b10 $
b10 )
b10 +
b10001010 '
1!
#2750000000000000
0!
#2760000000000000
b11 "
b11 $
b11 )
b11 +
b10001011 %
b10001011 (
b10001011 '
1!
#2770000000000000
0!
#2780000000000000
b10001100 %
b10001100 (
b1011 "
b1011 $
b1011 )
b1011 +
b10001100 '
1!
#2790000000000000
0!
#2800000000000000
b0 "
b0 $
b0 )
b0 +
b10001101 %
b10001101 (
b10001101 '
1!
#2810000000000000
0!
#2820000000000000
b10001110 %
b10001110 (
b1 "
b1 $
b1 )
b1 +
b10001110 '
1!
#2830000000000000
0!
#2840000000000000
b111 "
b111 $
b111 )
b111 +
b10001111 %
b10001111 (
b10001111 '
1!
#2850000000000000
0!
#2860000000000000
b10010000 %
b10010000 (
b10010000 '
1!
#2870000000000000
0!
#2880000000000000
b1111 "
b1111 $
b1111 )
b1111 +
b10010001 %
b10010001 (
b10010001 '
1!
#2890000000000000
0!
#2900000000000000
b10010010 %
b10010010 (
b1110 "
b1110 $
b1110 )
b1110 +
b10010010 '
1!
#2910000000000000
0!
#2920000000000000
b111 "
b111 $
b111 )
b111 +
b10010011 %
b10010011 (
b10010011 '
1!
#2930000000000000
0!
#2940000000000000
b10010100 %
b10010100 (
b1111 "
b1111 $
b1111 )
b1111 +
b10010100 '
1!
#2950000000000000
0!
#2960000000000000
b1100 "
b1100 $
b1100 )
b1100 +
b10010101 %
b10010101 (
b10010101 '
1!
#2970000000000000
0!
#2980000000000000
b10010110 %
b10010110 (
b1110 "
b1110 $
b1110 )
b1110 +
b10010110 '
1!
#2990000000000000
0!
#3000000000000000
b1101 "
b1101 $
b1101 )
b1101 +
b10010111 %
b10010111 (
b10010111 '
1!
#3010000000000000
0!
#3020000000000000
b10011000 %
b10011000 (
b111 "
b111 $
b111 )
b111 +
b10011000 '
1!
#3030000000000000
0!
#3040000000000000
b1010 "
b1010 $
b1010 )
b1010 +
b10011001 %
b10011001 (
b10011001 '
1!
#3050000000000000
0!
#3060000000000000
b10011010 %
b10011010 (
b1111 "
b1111 $
b1111 )
b1111 +
b10011010 '
1!
#3070000000000000
0!
#3080000000000000
b11 "
b11 $
b11 )
b11 +
b10011011 %
b10011011 (
b10011011 '
1!
#3090000000000000
0!
#3100000000000000
b10011100 %
b10011100 (
b0 "
b0 $
b0 )
b0 +
b10011100 '
1!
#3110000000000000
0!
#3120000000000000
b1111 "
b1111 $
b1111 )
b1111 +
b10011101 %
b10011101 (
b10011101 '
1!
#3130000000000000
0!
#3140000000000000
b10011110 %
b10011110 (
b1110 "
b1110 $
b1110 )
b1110 +
b10011110 '
1!
#3150000000000000
0!
#3160000000000000
b1101 "
b1101 $
b1101 )
b1101 +
b10011111 %
b10011111 (
b10011111 '
1!
#3170000000000000
0!
#3180000000000000
b10100000 %
b10100000 (
b1 "
b1 $
b1 )
b1 +
b10100000 '
1!
#3190000000000000
0!
#3200000000000000
b0 "
b0 $
b0 )
b0 +
b10100001 %
b10100001 (
b10100001 '
1!
#3210000000000000
0!
#3220000000000000
b10100010 %
b10100010 (
b1100 "
b1100 $
b1100 )
b1100 +
b10100010 '
1!
#3230000000000000
0!
#3240000000000000
b1000 "
b1000 $
b1000 )
b1000 +
b10100011 %
b10100011 (
b10100011 '
1!
#3250000000000000
0!
#3260000000000000
b10100100 %
b10100100 (
b1100 "
b1100 $
b1100 )
b1100 +
b10100100 '
1!
#3270000000000000
0!
#3280000000000000
b1011 "
b1011 $
b1011 )
b1011 +
b10100101 %
b10100101 (
b10100101 '
1!
#3290000000000000
0!
#3300000000000000
b10100110 %
b10100110 (
b101 "
b101 $
b101 )
b101 +
b10100110 '
1!
#3310000000000000
0!
#3320000000000000
b1111 "
b1111 $
b1111 )
b1111 +
b10100111 %
b10100111 (
b10100111 '
1!
#3330000000000000
0!
#3340000000000000
b10101000 %
b10101000 (
b1101 "
b1101 $
b1101 )
b1101 +
b10101000 '
1!
#3350000000000000
0!
#3360000000000000
b10101001 %
b10101001 (
b10101001 '
1!
#3370000000000000
0!
#3380000000000000
b10101010 %
b10101010 (
b1111 "
b1111 $
b1111 )
b1111 +
b10101010 '
1!
#3390000000000000
0!
#3400000000000000
b101 "
b101 $
b101 )
b101 +
b10101011 %
b10101011 (
b10101011 '
1!
#3410000000000000
0!
#3420000000000000
b10101100 %
b10101100 (
b1101 "
b1101 $
b1101 )
b1101 +
b10101100 '
1!
#3430000000000000
0!
#3440000000000000
b1111 "
b1111 $
b1111 )
b1111 +
b10101101 %
b10101101 (
b10101101 '
1!
#3450000000000000
0!
#3460000000000000
b10101110 %
b10101110 (
b101 "
b101 $
b101 )
b101 +
b10101110 '
1!
#3470000000000000
0!
#3480000000000000
b1010 "
b1010 $
b1010 )
b1010 +
b10101111 %
b10101111 (
b10101111 '
1!
#3490000000000000
0!
#3500000000000000
b10110000 %
b10110000 (
b10 "
b10 $
b10 )
b10 +
b10110000 '
1!
#3510000000000000
0!
#3520000000000000
b1011 "
b1011 $
b1011 )
b1011 +
b10110001 %
b10110001 (
b10110001 '
1!
#3530000000000000
0!
#3540000000000000
b10110010 %
b10110010 (
b111 "
b111 $
b111 )
b111 +
b10110010 '
1!
#3550000000000000
0!
#3560000000000000
b100 "
b100 $
b100 )
b100 +
b10110011 %
b10110011 (
b10110011 '
1!
#3570000000000000
0!
#3580000000000000
b10110100 %
b10110100 (
b1101 "
b1101 $
b1101 )
b1101 +
b10110100 '
1!
#3590000000000000
0!
#3600000000000000
b111 "
b111 $
b111 )
b111 +
b10110101 %
b10110101 (
b10110101 '
1!
#3610000000000000
0!
#3620000000000000
b10110110 %
b10110110 (
b101 "
b101 $
b101 )
b101 +
b10110110 '
1!
#3630000000000000
0!
#3640000000000000
b0 "
b0 $
b0 )
b0 +
b10110111 %
b10110111 (
b10110111 '
1!
#3650000000000000
0!
#3660000000000000
b10111000 %
b10111000 (
b1111 "
b1111 $
b1111 )
b1111 +
b10111000 '
1!
#3670000000000000
0!
#3680000000000000
b110 "
b110 $
b110 )
b110 +
b10111001 %
b10111001 (
b10111001 '
1!
#3690000000000000
0!
#3700000000000000
b10111010 %
b10111010 (
b1101 "
b1101 $
b1101 )
b1101 +
b10111010 '
1!
#3710000000000000
0!
#3720000000000000
b10 "
b10 $
b10 )
b10 +
b10111011 %
b10111011 (
b10111011 '
1!
#3730000000000000
0!
#3740000000000000
b10111100 %
b10111100 (
b11 "
b11 $
b11 )
b11 +
b10111100 '
1!
#3750000000000000
0!
#3760000000000000
b100 "
b100 $
b100 )
b100 +
b10111101 %
b10111101 (
b10111101 '
1!
#3770000000000000
0!
#3780000000000000
b10111110 %
b10111110 (
b1 "
b1 $
b1 )
b1 +
b10111110 '
1!
#3790000000000000
0!
#3800000000000000
b1100 "
b1100 $
b1100 )
b1100 +
b10111111 %
b10111111 (
b10111111 '
1!
#3810000000000000
0!
#3820000000000000
b11000000 %
b11000000 (
b1011 "
b1011 $
b1011 )
b1011 +
b11000000 '
1!
#3830000000000000
0!
#3840000000000000
b1111 "
b1111 $
b1111 )
b1111 +
b11000001 %
b11000001 (
b11000001 '
1!
#3850000000000000
0!
#3860000000000000
b11000010 %
b11000010 (
b111 "
b111 $
b111 )
b111 +
b11000010 '
1!
#3870000000000000
0!
#3880000000000000
b100 "
b100 $
b100 )
b100 +
b11000011 %
b11000011 (
b11000011 '
1!
#3890000000000000
0!
#3900000000000000
b11000100 %
b11000100 (
b1111 "
b1111 $
b1111 )
b1111 +
b11000100 '
1!
#3910000000000000
0!
#3920000000000000
b10 "
b10 $
b10 )
b10 +
b11000101 %
b11000101 (
b11000101 '
1!
#3930000000000000
0!
#3940000000000000
b11000110 %
b11000110 (
b110 "
b110 $
b110 )
b110 +
b11000110 '
1!
#3950000000000000
0!
#3960000000000000
b1011 "
b1011 $
b1011 )
b1011 +
b11000111 %
b11000111 (
b11000111 '
1!
#3970000000000000
0!
#3980000000000000
b11001000 %
b11001000 (
b1000 "
b1000 $
b1000 )
b1000 +
b11001000 '
1!
#3990000000000000
0!
#4000000000000000
b1001 "
b1001 $
b1001 )
b1001 +
b11001001 %
b11001001 (
b11001001 '
1!
#4010000000000000
0!
#4020000000000000
b11001010 %
b11001010 (
b1100 "
b1100 $
b1100 )
b1100 +
b11001010 '
1!
#4030000000000000
0!
#4040000000000000
b1001 "
b1001 $
b1001 )
b1001 +
b11001011 %
b11001011 (
b11001011 '
1!
#4050000000000000
0!
#4060000000000000
b11001100 %
b11001100 (
b1010 "
b1010 $
b1010 )
b1010 +
b11001100 '
1!
#4070000000000000
0!
#4080000000000000
b101 "
b101 $
b101 )
b101 +
b11001101 %
b11001101 (
b11001101 '
1!
#4090000000000000
0!
#4100000000000000
b11001110 %
b11001110 (
b111 "
b111 $
b111 )
b111 +
b11001110 '
1!
#4110000000000000
0!
#4120000000000000
b10 "
b10 $
b10 )
b10 +
b11001111 %
b11001111 (
b11001111 '
1!
#4130000000000000
0!
#4140000000000000
b11010000 %
b11010000 (
b1111 "
b1111 $
b1111 )
b1111 +
b11010000 '
1!
#4150000000000000
0!
#4160000000000000
b1011 "
b1011 $
b1011 )
b1011 +
b11010001 %
b11010001 (
b11010001 '
1!
#4170000000000000
0!
#4180000000000000
b11010010 %
b11010010 (
b1110 "
b1110 $
b1110 )
b1110 +
b11010010 '
1!
#4190000000000000
0!
#4200000000000000
b1111 "
b1111 $
b1111 )
b1111 +
b11010011 %
b11010011 (
b11010011 '
1!
#4210000000000000
0!
#4220000000000000
b11010100 %
b11010100 (
b110 "
b110 $
b110 )
b110 +
b11010100 '
1!
#4230000000000000
0!
#4240000000000000
b10 "
b10 $
b10 )
b10 +
b11010101 %
b11010101 (
b11010101 '
1!
#4250000000000000
0!
#4260000000000000
b11010110 %
b11010110 (
b101 "
b101 $
b101 )
b101 +
b11010110 '
1!
#4270000000000000
0!
#4280000000000000
b1001 "
b1001 $
b1001 )
b1001 +
b11010111 %
b11010111 (
b11010111 '
1!
#4290000000000000
0!
#4300000000000000
b11011000 %
b11011000 (
b11011000 '
1!
#4310000000000000
0!
#4320000000000000
b1111 "
b1111 $
b1111 )
b1111 +
b11011001 %
b11011001 (
b11011001 '
1!
#4330000000000000
0!
#4340000000000000
b11011010 %
b11011010 (
b1101 "
b1101 $
b1101 )
b1101 +
b11011010 '
1!
#4350000000000000
0!
#4360000000000000
b110 "
b110 $
b110 )
b110 +
b11011011 %
b11011011 (
b11011011 '
1!
#4370000000000000
0!
#4380000000000000
b11011100 %
b11011100 (
b1101 "
b1101 $
b1101 )
b1101 +
b11011100 '
1!
#4390000000000000
0!
#4400000000000000
b1000 "
b1000 $
b1000 )
b1000 +
b11011101 %
b11011101 (
b11011101 '
1!
#4410000000000000
0!
#4420000000000000
b11011110 %
b11011110 (
b0 "
b0 $
b0 )
b0 +
b11011110 '
1!
