A3/adder.v
`timescale 1ns / 1ps

module adder (
    input wire inA,
    input wire inB,
    input wire inC,
    output wire sum,
    output wire cout
);

assign sum = inA ^ inB ^ inC;
assign cout = (inA & inB) | (inA & inC) | (inB & inC);

endmodule

module adder4ripple (
    input [3:0] inA, inB,
    output [3:0] sum, cout
);

genvar i;
generate
    for (i = 0; i < 4; i = i + 1) begin
        if (i == 0)
            adder hoge (inA[i], inB[i], 0, sum[i], cout[i]);
        else
            adder hoge (inA[i], inB[i], cout[i - 1], sum[i], cout[i]);
    end
endgenerate

endmodule

module adder4 (
    input [3:0] inA, inB,
    output [3:0] sum,
    output wire is_overflowed
);

assign sum = inA + inB;
assign is_overflowed = (~inA[3] & ~inB[3] & sum[3]) | (inA[3] & inB[3] & ~sum[3]);

endmodule

A3/sim_adder4.v
module sim_adder4;
    
    // parameter
    parameter HALF_CYCLE = 100;
    
    // wire/reg
    reg [3:0] inA, inB;
    wire [3:0] S_r, C_r, S;
    wire is_overflowed;

    adder4ripple adder4ripple_mod(
        .inA(inA),
        .inB(inB),
        .sum(S_r),
        .cout(C_r)
    );

    adder4 adder4_mod(
        .inA(inA),
        .inB(inB),
        .sum(S),
        .is_overflowed(is_overflowed)
    );

    // test scenario
    initial begin
    
        $dumpfile("app.vcd");
        $dumpvars(0, sim_adder4);   

        for (integer i = 0; i < 16; i = i + 1) begin
          inA <= i;
            for (integer j = 0; j < 16; j = j + 1) begin
              inB <= j;
              #100 $display("inA=%b, inB=%b, S_r=%b, S=%b (%s)%s", inA, inB, S_r, S,
                  S_r == S ? "OK" : "NG",
                  is_overflowed ? " overflowed": ""
              );
            end
        end
        
        $finish;
    end

endmodule

A3/app.vcd
$date
	Thu Apr 18 15:50:10 2024
$end
$version
	Icarus Verilog
$end
$timescale
	1ps
$end
$scope module sim_adder4 $end
$var wire 1 ! is_overflowed $end
$var wire 4 " S_r [3:0] $end
$var wire 4 # S [3:0] $end
$var wire 4 $ C_r [3:0] $end
$var reg 4 % inA [3:0] $end
$var reg 4 & inB [3:0] $end
$scope module adder4_mod $end
$var wire 4 ' inA [3:0] $end
$var wire 4 ( inB [3:0] $end
$var wire 1 ! is_overflowed $end
$var wire 4 ) sum [3:0] $end
$upscope $end
$scope module adder4ripple_mod $end
$var wire 4 * inA [3:0] $end
$var wire 4 + inB [3:0] $end
$var wire 4 , sum [3:0] $end
$var wire 4 - cout [3:0] $end
$scope begin genblk1[0] $end
$scope begin genblk2 $end
$scope module hoge $end
$var wire 1 . cout $end
$var wire 1 / inA $end
$var wire 1 0 inB $end
$var wire 1 1 inC $end
$var wire 1 2 sum $end
$upscope $end
$upscope $end
$upscope $end
$scope begin genblk1[1] $end
$scope begin genblk3 $end
$scope module hoge $end
$var wire 1 3 cout $end
$var wire 1 4 inA $end
$var wire 1 5 inB $end
$var wire 1 6 inC $end
$var wire 1 7 sum $end
$upscope $end
$upscope $end
$upscope $end
$scope begin genblk1[2] $end
$scope begin genblk3 $end
$scope module hoge $end
$var wire 1 8 cout $end
$var wire 1 9 inA $end
$var wire 1 : inB $end
$var wire 1 ; inC $end
$var wire 1 < sum $end
$upscope $end
$upscope $end
$upscope $end
$scope begin genblk1[3] $end
$scope begin genblk3 $end
$scope module hoge $end
$var wire 1 = cout $end
$var wire 1 > inA $end
$var wire 1 ? inB $end
$var wire 1 @ inC $end
$var wire 1 A sum $end
$upscope $end
$upscope $end
$upscope $end
$upscope $end
$scope begin $ivl_for_loop0 $end
$var integer 32 B i [31:0] $end
$scope begin $ivl_for_loop1 $end
$var integer 32 C j [31:0] $end
$upscope $end
$upscope $end
$upscope $end
$enddefinitions $end
#0
$dumpvars
b0 C
b0 B
0A
0@
0?
0>
0=
0<
0;
0:
09
08
07
06
05
04
03
02
01
00
0/
0.
b0 -
b0 ,
b0 +
b0 *
b0 )
b0 (
b0 '
b0 &
b0 %
b0 $
b0 #
b0 "
0!
$end
#100000
b1 "
b1 ,
12
10
b1 #
b1 )
b1 &
b1 (
b1 +
b1 C
#200000
02
b10 "
b10 ,
17
00
15
b10 #
b10 )
b10 &
b10 (
b10 +
b10 C
#300000
b11 "
b11 ,
12
10
b11 #
b11 )
b11 &
b11 (
b11 +
b11 C
#400000
02
07
b100 "
b100 ,
1<
00
05
1:
b100 #
b100 )
b100 &
b100 (
b100 +
b100 C
#500000
b101 "
b101 ,
12
10
b101 #
b101 )
b101 &
b101 (
b101 +
b101 C
#600000
02
b110 "
b110 ,
17
00
15
b110 #
b110 )
b110 &
b110 (
b110 +
b110 C
#700000
b111 "
b111 ,
12
10
b111 #
b111 )
b111 &
b111 (
b111 +
b111 C
#800000
0!
02
07
0<
b1000 "
b1000 ,
1A
00
05
0:
1?
b1000 #
b1000 )
b1000 &
b1000 (
b1000 +
b1000 C
#900000
b1001 "
b1001 ,
12
10
b1001 #
b1001 )
b1001 &
b1001 (
b1001 +
b1001 C
#1000000
02
b1010 "
b1010 ,
17
00
15
b1010 #
b1010 )
b1010 &
b1010 (
b1010 +
b1010 C
#1100000
b1011 "
b1011 ,
12
10
b1011 #
b1011 )
b1011 &
b1011 (
b1011 +
b1011 C
#1200000
02
07
b1100 "
b1100 ,
1<
00
05
1:
b1100 #
b1100 )
b1100 &
b1100 (
b1100 +
b1100 C
#1300000
b1101 "
b1101 ,
12
10
b1101 #
b1101 )
b1101 &
b1101 (
b1101 +
b1101 C
#1400000
02
b1110 "
b1110 ,
17
00
15
b1110 #
b1110 )
b1110 &
b1110 (
b1110 +
b1110 C
#1500000
b1111 "
b1111 ,
12
10
b1111 #
b1111 )
b1111 &
b1111 (
b1111 +
b1111 C
#1600000
07
0<
b1 "
b1 ,
0A
00
05
0:
0?
1/
b0 &
b0 (
b0 +
b1 #
b1 )
b1 %
b1 '
b1 *
b1 B
b0 C
#1700000
17
16
b1 $
b1 -
1.
b10 "
b10 ,
02
10
b10 #
b10 )
b1 &
b1 (
b1 +
b1 C
#1800000
06
0<
0.
0;
12
b11 "
b11 ,
17
b0 $
b0 -
03
00
15
b11 #
b11 )
b10 &
b10 (
b10 +
b10 C
#1900000
1<
1;
13
07
16
b11 $
b11 -
1.
b100 "
b100 ,
02
10
b100 #
b100 )
b11 &
b11 (
b11 +
b11 C
#2000000
06
0A
0.
0;
0@
12
07
03
b101 "
b101 ,
1<
b0 $
b0 -
08
00
05
1:
b101 #
b101 )
b100 &
b100 (
b100 +
b100 C
#2100000
17
16
b1 $
b1 -
1.
b110 "
b110 ,
02
10
b110 #
b110 )
b101 &
b101 (
b101 +
b101 C
#2200000
0A
0@
08
06
1<
0.
0;
12
b111 "
b111 ,
17
b0 $
b0 -
03
00
15
b111 #
b111 )
b110 &
b110 (
b110 +
b110 C
#2300000
1A
1@
18
0<
1;
13
07
16
b111 $
b111 -
1.
1!
b1000 "
b1000 ,
02
10
b1000 #
b1000 )
b111 &
b111 (
b111 +
b111 C
#2400000
0!
06
0.
0;
0@
12
07
03
0<
08
b1001 "
b1001 ,
1A
b0 $
b0 -
0=
00
05
0:
1?
b1001 #
b1001 )
b1000 &
b1000 (
b1000 +
b1000 C
#2500000
17
16
b1 $
b1 -
1.
b1010 "
b1010 ,
02
10
b1010 #
b1010 )
b1001 &
b1001 (
b1001 +
b1001 C
#2600000
06
0<
0.
0;
12
b1011 "
b1011 ,
17
b0 $
b0 -
03
00
15
b1011 #
b1011 )
b1010 &
b1010 (
b1010 +
b1010 C
#2700000
1<
1;
13
07
16
b11 $
b11 -
1.
b1100 "
b1100 ,
02
10
b1100 #
b1100 )
b1011 &
b1011 (
b1011 +
b1011 C
#2800000
0=
06
1A
0.
0;
0@
12
07
03
b1101 "
b1101 ,
1<
b0 $
b0 -
08
00
05
1:
b1101 #
b1101 )
b1100 &
b1100 (
b1100 +
b1100 C
#2900000
17
16
b1 $
b1 -
1.
b1110 "
b1110 ,
02
10
b1110 #
b1110 )
b1101 &
b1101 (
b1101 +
b1101 C
#3000000
0=
1A
0@
08
06
1<
0.
0;
12
b1111 "
b1111 ,
17
b0 $
b0 -
03
00
15
b1111 #
b1111 )
b1110 &
b1110 (
b1110 +
b1110 C
#3100000
1=
0A
1@
18
0<
1;
13
07
16
b1111 $
b1111 -
1.
b0 "
b0 ,
02
10
b0 #
b0 )
b1111 &
b1111 (
b1111 +
b1111 C
#3200000
0;
03
17
06
0@
0.
0<
08
b10 "
b10 ,
0A
b0 $
b0 -
0=
00
05
0:
0?
0/
14
b0 &
b0 (
b0 +
b10 #
b10 )
b10 %
b10 '
b10 *
b10 B
b0 C
#3300000
b11 "
b11 ,
12
10
b11 #
b11 )
b1 &
b1 (
b1 +
b1 C
#3400000
1<
1;
b10 $
b10 -
13
02
b100 "
b100 ,
07
00
15
b100 #
b100 )
b10 &
b10 (
b10 +
b10 C
#3500000
b101 "
b101 ,
12
10
b101 #
b101 )
b11 &
b11 (
b11 +
b11 C
#3600000
0;
0A
03
0@
02
17
b110 "
b110 ,
1<
b0 $
b0 -
08
00
05
1:
b110 #
b110 )
b100 &
b100 (
b100 +
b100 C
#3700000
b111 "
b111 ,
12
10
b111 #
b111 )
b101 &
b101 (
b101 +
b101 C
#3800000
1A
1@
18
0<
1;
b110 $
b110 -
13
1!
02
b1000 "
b1000 ,
07
00
15
b1000 #
b1000 )
b110 &
b110 (
b110 +
b110 C
#3900000
b1001 "
b1001 ,
12
10
b1001 #
b1001 )
b111 &
b111 (
b111 +
b111 C
#4000000
0!
0;
03
0@
02
17
0<
08
b1010 "
b1010 ,
1A
b0 $
b0 -
0=
00
05
0:
1?
b1010 #
b1010 )
b1000 &
b1000 (
b1000 +
b1000 C
#4100000
b1011 "
b1011 ,
12
10
b1011 #
b1011 )
b1001 &
b1001 (
b1001 +
b1001 C
#4200000
1<
1;
b10 $
b10 -
13
02
b1100 "
b1100 ,
07
00
15
b1100 #
b1100 )
b1010 &
b1010 (
b1010 +
b1010 C
#4300000
b1101 "
b1101 ,
12
10
b1101 #
b1101 )
b1011 &
b1011 (
b1011 +
b1011 C
#4400000
0=
0;
1A
03
0@
02
17
b1110 "
b1110 ,
1<
b0 $
b0 -
08
00
05
1:
b1110 #
b1110 )
b1100 &
b1100 (
b1100 +
b1100 C
#4500000
b1111 "
b1111 ,
12
10
b1111 #
b1111 )
b1101 &
b1101 (
b1101 +
b1101 C
#4600000
1=
0A
1@
18
0<
1;
b1110 $
b1110 -
13
02
b0 "
b0 ,
07
00
15
b0 #
b0 )
b1110 &
b1110 (
b1110 +
b1110 C
#4700000
b1 "
b1 ,
12
10
b1 #
b1 )
b1111 &
b1111 (
b1111 +
b1111 C
#4800000
0;
03
0@
17
0<
08
b11 "
b11 ,
0A
b0 $
b0 -
0=
00
05
0:
0?
1/
b0 &
b0 (
b0 +
b11 #
b11 )
b11 %
b11 '
b11 *
b11 B
b0 C
#4900000
1<
1;
13
07
16
b11 $
b11 -
1.
b100 "
b100 ,
02
10
b100 #
b100 )
b1 &
b1 (
b1 +
b1 C
#5000000
06
b10 $
b10 -
0.
12
b101 "
b101 ,
07
00
15
b101 #
b101 )
b10 &
b10 (
b10 +
b10 C
#5100000
17
16
b11 $
b11 -
1.
b110 "
b110 ,
02
10
b110 #
b110 )
b11 &
b11 (
b11 +
b11 C
#5200000
0;
03
06
0A
0.
0@
12
17
b111 "
b111 ,
1<
b0 $
b0 -
08
00
05
1:
b111 #
b111 )
b100 &
b100 (
b100 +
b100 C
#5300000
1A
1@
18
0<
1;
13
07
16
b111 $
b111 -
1.
1!
b1000 "
b1000 ,
02
10
b1000 #
b1000 )
b101 &
b101 (
b101 +
b101 C
#5400000
06
b110 $
b110 -
0.
12
b1001 "
b1001 ,
07
00
15
b1001 #
b1001 )
b110 &
b110 (
b110 +
b110 C
#5500000
17
16
b111 $
b111 -
1.
b1010 "
b1010 ,
02
10
b1010 #
b1010 )
b111 &
b111 (
b111 +
b111 C
#5600000
0;
03
0!
06
0.
0@
12
17
0<
08
b1011 "
b1011 ,
1A
b0 $
b0 -
0=
00
05
0:
1?
b1011 #
b1011 )
b1000 &
b1000 (
b1000 +
b1000 C
#5700000
1<
1;
13
07
16
b11 $
b11 -
1.
b1100 "
b1100 ,
02
10
b1100 #
b1100 )
b1001 &
b1001 (
b1001 +
b1001 C
#5800000
06
b10 $
b10 -
0.
12
b1101 "
b1101 ,
07
00
15
b1101 #
b1101 )
b1010 &
b1010 (
b1010 +
b1010 C
#5900000
17
16
b11 $
b11 -
1.
b1110 "
b1110 ,
02
10
b1110 #
b1110 )
b1011 &
b1011 (
b1011 +
b1011 C
#6000000
0;
03
0=
06
1A
0.
0@
12
17
b1111 "
b1111 ,
1<
b0 $
b0 -
08
00
05
1:
b1111 #
b1111 )
b1100 &
b1100 (
b1100 +
b1100 C
#6100000
1=
0A
1@
18
0<
1;
13
07
16
b1111 $
b1111 -
1.
b0 "
b0 ,
02
10
b0 #
b0 )
b1101 &
b1101 (
b1101 +
b1101 C
#6200000
06
b1110 $
b1110 -
0.
12
b1 "
b1 ,
07
00
15
b1 #
b1 )
b1110 &
b1110 (
b1110 +
b1110 C
#6300000
17
16
b1111 $
b1111 -
1.
b10 "
b10 ,
02
10
b10 #
b10 )
b1111 &
b1111 (
b1111 +
b1111 C
#6400000
0@
08
07
1<
06
0;
0.
03
b100 "
b100 ,
0A
b0 $
b0 -
0=
00
05
0:
0?
0/
04
19
b0 &
b0 (
b0 +
b100 #
b100 )
b100 %
b100 '
b100 *
b100 B
b0 C
#6500000
b101 "
b101 ,
12
10
b101 #
b101 )
b1 &
b1 (
b1 +
b1 C
#6600000
02
b110 "
b110 ,
17
00
15
b110 #
b110 )
b10 &
b10 (
b10 +
b10 C
#6700000
b111 "
b111 ,
12
10
b111 #
b111 )
b11 &
b11 (
b11 +
b11 C
#6800000
1A
1@
b100 $
b100 -
18
1!
02
07
b1000 "
b1000 ,
0<
00
05
1:
b1000 #
b1000 )
b100 &
b100 (
b100 +
b100 C
#6900000
b1001 "
b1001 ,
12
10
b1001 #
b1001 )
b101 &
b101 (
b101 +
b101 C
#7000000
02
b1010 "
b1010 ,
17
00
15
b1010 #
b1010 )
b110 &
b110 (
b110 +
b110 C
#7100000
b1011 "
b1011 ,
12
10
b1011 #
b1011 )
b111 &
b111 (
b111 +
b111 C
#7200000
0!
0@
08
02
07
1<
b1100 "
b1100 ,
1A
b0 $
b0 -
0=
00
05
0:
1?
b1100 #
b1100 )
b1000 &
b1000 (
b1000 +
b1000 C
#7300000
b1101 "
b1101 ,
12
10
b1101 #
b1101 )
b1001 &
b1001 (
b1001 +
b1001 C
#7400000
02
b1110 "
b1110 ,
17
00
15
b1110 #
b1110 )
b1010 &
b1010 (
b1010 +
b1010 C
#7500000
b1111 "
b1111 ,
12
10
b1111 #
b1111 )
b1011 &
b1011 (
b1011 +
b1011 C
#7600000
1=
0A
1@
b1100 $
b1100 -
18
02
07
b0 "
b0 ,
0<
00
05
1:
b0 #
b0 )
b1100 &
b1100 (
b1100 +
b1100 C
#7700000
b1 "
b1 ,
12
10
b1 #
b1 )
b1101 &
b1101 (
b1101 +
b1101 C
#7800000
02
b10 "
b10 ,
17
00
15
b10 #
b10 )
b1110 &
b1110 (
b1110 +
b1110 C
#7900000
b11 "
b11 ,
12
10
b11 #
b11 )
b1111 &
b1111 (
b1111 +
b1111 C
#8000000
0@
08
07
1<
b101 "
b101 ,
0A
b0 $
b0 -
0=
00
05
0:
0?
1/
b0 &
b0 (
b0 +
b101 #
b101 )
b101 %
b101 '
b101 *
b101 B
b0 C
#8100000
17
16
b1 $
b1 -
1.
b110 "
b110 ,
02
10
b110 #
b110 )
b1 &
b1 (
b1 +
b1 C
#8200000
0A
0@
08
06
1<
0.
0;
12
b111 "
b111 ,
17
b0 $
b0 -
03
00
15
b111 #
b111 )
b10 &
b10 (
b10 +
b10 C
#8300000
1A
1@
18
0<
1;
13
07
16
b111 $
b111 -
1.
1!
b1000 "
b1000 ,
02
10
b1000 #
b1000 )
b11 &
b11 (
b11 +
b11 C
#8400000
06
0.
0;
12
07
b100 $
b100 -
03
b1001 "
b1001 ,
0<
00
05
1:
b1001 #
b1001 )
b100 &
b100 (
b100 +
b100 C
#8500000
17
16
b101 $
b101 -
1.
b1010 "
b1010 ,
02
10
b1010 #
b1010 )
b101 &
b101 (
b101 +
b101 C
#8600000
06
0<
0.
0;
12
b1011 "
b1011 ,
17
b100 $
b100 -
03
00
15
b1011 #
b1011 )
b110 &
b110 (
b110 +
b110 C
#8700000
1<
1;
13
07
16
b111 $
b111 -
1.
b1100 "
b1100 ,
02
10
b1100 #
b1100 )
b111 &
b111 (
b111 +
b111 C
#8800000
0@
08
0!
06
0.
0;
12
07
03
1<
b1101 "
b1101 ,
1A
b0 $
b0 -
0=
00
05
0:
1?
b1101 #
b1101 )
b1000 &
b1000 (
b1000 +
b1000 C
#8900000
17
16
b1 $
b1 -
1.
b1110 "
b1110 ,
02
10
b1110 #
b1110 )
b1001 &
b1001 (
b1001 +
b1001 C
#9000000
0=
1A
0@
08
06
1<
0.
0;
12
b1111 "
b1111 ,
17
b0 $
b0 -
03
00
15
b1111 #
b1111 )
b1010 &
b1010 (
b1010 +
b1010 C
#9100000
1=
0A
1@
18
0<
1;
13
07
16
b1111 $
b1111 -
1.
b0 "
b0 ,
02
10
b0 #
b0 )
b1011 &
b1011 (
b1011 +
b1011 C
#9200000
06
0.
0;
12
07
b1100 $
b1100 -
03
b1 "
b1 ,
0<
00
05
1:
b1 #
b1 )
b1100 &
b1100 (
b1100 +
b1100 C
#9300000
17
16
b1101 $
b1101 -
1.
b10 "
b10 ,
02
10
b10 #
b10 )
b1101 &
b1101 (
b1101 +
b1101 C
#9400000
06
0<
0.
0;
12
b11 "
b11 ,
17
b1100 $
b1100 -
03
00
15
b11 #
b11 )
b1110 &
b1110 (
b1110 +
b1110 C
#9500000
1<
1;
13
07
16
b1111 $
b1111 -
1.
b100 "
b100 ,
02
10
b100 #
b100 )
b1111 &
b1111 (
b1111 +
b1111 C
#9600000
0@
08
0;
03
17
06
0.
1<
b110 "
b110 ,
0A
b0 $
b0 -
0=
00
05
0:
0?
0/
14
b0 &
b0 (
b0 +
b110 #
b110 )
b110 %
b110 '
b110 *
b110 B
b0 C
#9700000
b111 "
b111 ,
12
10
b111 #
b111 )
b1 &
b1 (
b1 +
b1 C
#9800000
1A
1@
18
0<
1;
b110 $
b110 -
13
1!
02
b1000 "
b1000 ,
07
00
15
b1000 #
b1000 )
b10 &
b10 (
b10 +
b10 C
#9900000
b1001 "
b1001 ,
12
10
b1001 #
b1001 )
b11 &
b11 (
b11 +
b11 C
#10000000
0;
b100 $
b100 -
03
02
17
b1010 "
b1010 ,
0<
00
05
1:
b1010 #
b1010 )
b100 &
b100 (
b100 +
b100 C
#10100000
b1011 "
b1011 ,
12
10
b1011 #
b1011 )
b101 &
b101 (
b101 +
b101 C
#10200000
1<
1;
b110 $
b110 -
13
02
b1100 "
b1100 ,
07
00
15
b1100 #
b1100 )
b110 &
b110 (
b110 +
b110 C
#10300000
b1101 "
b1101 ,
12
10
b1101 #
b1101 )
b111 &
b111 (
b111 +
b111 C
#10400000
0@
08
0!
0;
03
02
17
1<
b1110 "
b1110 ,
1A
b0 $
b0 -
0=
00
05
0:
1?
b1110 #
b1110 )
b1000 &
b1000 (
b1000 +
b1000 C
#10500000
b1111 "
b1111 ,
12
10
b1111 #
b1111 )
b1001 &
b1001 (
b1001 +
b1001 C
#10600000
1=
0A
1@
18
0<
1;
b1110 $
b1110 -
13
02
b0 "
b0 ,
07
00
15
b0 #
b0 )
b1010 &
b1010 (
b1010 +
b1010 C
#10700000
b1 "
b1 ,
12
10
b1 #
b1 )
b1011 &
b1011 (
b1011 +
b1011 C
#10800000
0;
b1100 $
b1100 -
03
02
17
b10 "
b10 ,
0<
00
05
1:
b10 #
b10 )
b1100 &
b1100 (
b1100 +
b1100 C
#10900000
b11 "
b11 ,
12
10
b11 #
b11 )
b1101 &
b1101 (
b1101 +
b1101 C
#11000000
1<
1;
b1110 $
b1110 -
13
02
b100 "
b100 ,
07
00
15
b100 #
b100 )
b1110 &
b1110 (
b1110 +
b1110 C
#11100000
b101 "
b101 ,
12
10
b101 #
b101 )
b1111 &
b1111 (
b1111 +
b1111 C
#11200000
0@
08
0;
03
17
1<
b111 "
b111 ,
0A
b0 $
b0 -
0=
00
05
0:
0?
1/
b0 &
b0 (
b0 +
b111 #
b111 )
b111 %
b111 '
b111 *
b111 B
b0 C
#11300000
1A
1@
18
0<
1;
13
07
16
b111 $
b111 -
1.
1!
b1000 "
b1000 ,
02
10
b1000 #
b1000 )
b1 &
b1 (
b1 +
b1 C
#11400000
06
b110 $
b110 -
0.
12
b1001 "
b1001 ,
07
00
15
b1001 #
b1001 )
b10 &
b10 (
b10 +
b10 C
#11500000
17
16
b111 $
b111 -
1.
b1010 "
b1010 ,
02
10
b1010 #
b1010 )
b11 &
b11 (
b11 +
b11 C
#11600000
0;
03
06
b100 $
b100 -
0.
12
17
b1011 "
b1011 ,
0<
00
05
1:
b1011 #
b1011 )
b100 &
b100 (
b100 +
b100 C
#11700000
1<
1;
13
07
16
b111 $
b111 -
1.
b1100 "
b1100 ,
02
10
b1100 #
b1100 )
b101 &
b101 (
b101 +
b101 C
#11800000
06
b110 $
b110 -
0.
12
b1101 "
b1101 ,
07
00
15
b1101 #
b1101 )
b110 &
b110 (
b110 +
b110 C
#11900000
17
16
b111 $
b111 -
1.
b1110 "
b1110 ,
02
10
b1110 #
b1110 )
b111 &
b111 (
b111 +
b111 C
#12000000
0@
08
0;
03
0!
06
0.
12
17
1<
b1111 "
b1111 ,
1A
b0 $
b0 -
0=
00
05
0:
1?
b1111 #
b1111 )
b1000 &
b1000 (
b1000 +
b1000 C
#12100000
1=
0A
1@
18
0<
1;
13
07
16
b1111 $
b1111 -
1.
b0 "
b0 ,
02
10
b0 #
b0 )
b1001 &
b1001 (
b1001 +
b1001 C
#12200000
06
b1110 $
b1110 -
0.
12
b1 "
b1 ,
07
00
15
b1 #
b1 )
b1010 &
b1010 (
b1010 +
b1010 C
#12300000
17
16
b1111 $
b1111 -
1.
b10 "
b10 ,
02
10
b10 #
b10 )
b1011 &
b1011 (
b1011 +
b1011 C
#12400000
0;
03
06
b1100 $
b1100 -
0.
12
17
b11 "
b11 ,
0<
00
05
1:
b11 #
b11 )
b1100 &
b1100 (
b1100 +
b1100 C
#12500000
1<
1;
13
07
16
b1111 $
b1111 -
1.
b100 "
b100 ,
02
10
b100 #
b100 )
b1101 &
b1101 (
b1101 +
b1101 C
#12600000
06
b1110 $
b1110 -
0.
12
b101 "
b101 ,
07
00
15
b101 #
b101 )
b1110 &
b1110 (
b1110 +
b1110 C
#12700000
17
16
b1111 $
b1111 -
1.
b110 "
b110 ,
02
10
b110 #
b110 )
b1111 &
b1111 (
b1111 +
b1111 C
#12800000
0=
07
0<
b1000 "
b1000 ,
1A
06
0;
0@
0.
03
b0 $
b0 -
08
00
05
0:
0?
0/
04
09
1>
b0 &
b0 (
b0 +
b1000 #
b1000 )
b1000 %
b1000 '
b1000 *
b1000 B
b0 C
#12900000
b1001 "
b1001 ,
12
10
b1001 #
b1001 )
b1 &
b1 (
b1 +
b1 C
#13000000
02
b1010 "
b1010 ,
17
00
15
b1010 #
b1010 )
b10 &
b10 (
b10 +
b10 C
#13100000
b1011 "
b1011 ,
12
10
b1011 #
b1011 )
b11 &
b11 (
b11 +
b11 C
#13200000
02
07
b1100 "
b1100 ,
1<
00
05
1:
b1100 #
b1100 )
b100 &
b100 (
b100 +
b100 C
#13300000
b1101 "
b1101 ,
12
10
b1101 #
b1101 )
b101 &
b101 (
b101 +
b101 C
#13400000
02
b1110 "
b1110 ,
17
00
15
b1110 #
b1110 )
b110 &
b110 (
b110 +
b110 C
#13500000
b1111 "
b1111 ,
12
10
b1111 #
b1111 )
b111 &
b111 (
b111 +
b111 C
#13600000
1!
b1000 $
b1000 -
1=
02
07
0<
b0 "
b0 ,
0A
00
05
0:
1?
b0 #
b0 )
b1000 &
b1000 (
b1000 +
b1000 C
#13700000
b1 "
b1 ,
12
10
b1 #
b1 )
b1001 &
b1001 (
b1001 +
b1001 C
#13800000
02
b10 "
b10 ,
17
00
15
b10 #
b10 )
b1010 &
b1010 (
b1010 +
b1010 C
#13900000
b11 "
b11 ,
12
10
b11 #
b11 )
b1011 &
b1011 (
b1011 +
b1011 C
#14000000
02
07
b100 "
b100 ,
1<
00
05
1:
b100 #
b100 )
b1100 &
b1100 (
b1100 +
b1100 C
#14100000
b101 "
b101 ,
12
10
b101 #
b101 )
b1101 &
b1101 (
b1101 +
b1101 C
#14200000
02
b110 "
b110 ,
17
00
15
b110 #
b110 )
b1110 &
b1110 (
b1110 +
b1110 C
#14300000
b111 "
b111 ,
12
10
b111 #
b111 )
b1111 &
b1111 (
b1111 +
b1111 C
#14400000
b0 $
b0 -
0=
0!
07
0<
b1001 "
b1001 ,
1A
00
05
0:
0?
1/
b0 &
b0 (
b0 +
b1001 #
b1001 )
b1001 %
b1001 '
b1001 *
b1001 B
b0 C
#14500000
17
16
b1 $
b1 -
1.
b1010 "
b1010 ,
02
10
b1010 #
b1010 )
b1 &
b1 (
b1 +
b1 C
#14600000
06
0<
0.
0;
12
b1011 "
b1011 ,
17
b0 $
b0 -
03
00
15
b1011 #
b1011 )
b10 &
b10 (
b10 +
b10 C
#14700000
1<
1;
13
07
16
b11 $
b11 -
1.
b1100 "
b1100 ,
02
10
b1100 #
b1100 )
b11 &
b11 (
b11 +
b11 C
#14800000
0=
06
1A
0.
0;
0@
12
07
03
b1101 "
b1101 ,
1<
b0 $
b0 -
08
00
05
1:
b1101 #
b1101 )
b100 &
b100 (
b100 +
b100 C
#14900000
17
16
b1 $
b1 -
1.
b1110 "
b1110 ,
02
10
b1110 #
b1110 )
b101 &
b101 (
b101 +
b101 C
#15000000
0=
1A
0@
08
06
1<
0.
0;
12
b1111 "
b1111 ,
17
b0 $
b0 -
03
00
15
b1111 #
b1111 )
b110 &
b110 (
b110 +
b110 C
#15100000
1=
0A
1@
18
0<
1;
13
07
16
b1111 $
b1111 -
1.
b0 "
b0 ,
02
10
b0 #
b0 )
b111 &
b111 (
b111 +
b111 C
#15200000
06
1!
0.
0;
0@
12
07
03
0<
b1000 $
b1000 -
08
b1 "
b1 ,
0A
00
05
0:
1?
b1 #
b1 )
b1000 &
b1000 (
b1000 +
b1000 C
#15300000
17
16
b1001 $
b1001 -
1.
b10 "
b10 ,
02
10
b10 #
b10 )
b1001 &
b1001 (
b1001 +
b1001 C
#15400000
06
0<
0.
0;
12
b11 "
b11 ,
17
b1000 $
b1000 -
03
00
15
b11 #
b11 )
b1010 &
b1010 (
b1010 +
b1010 C
#15500000
1<
1;
13
07
16
b1011 $
b1011 -
1.
b100 "
b100 ,
02
10
b100 #
b100 )
b1011 &
b1011 (
b1011 +
b1011 C
#15600000
06
0A
0.
0;
0@
12
07
03
b101 "
b101 ,
1<
b1000 $
b1000 -
08
00
05
1:
b101 #
b101 )
b1100 &
b1100 (
b1100 +
b1100 C
#15700000
17
16
b1001 $
b1001 -
1.
b110 "
b110 ,
02
10
b110 #
b110 )
b1101 &
b1101 (
b1101 +
b1101 C
#15800000
0A
0@
08
06
1<
0.
0;
12
b111 "
b111 ,
17
b1000 $
b1000 -
03
00
15
b111 #
b111 )
b1110 &
b1110 (
b1110 +
b1110 C
#15900000
1A
1@
18
0<
1;
13
07
16
0!
b1111 $
b1111 -
1.
b1000 "
b1000 ,
02
10
b1000 #
b1000 )
b1111 &
b1111 (
b1111 +
b1111 C
#16000000
0;
03
0=
17
06
0@
0.
0<
b0 $
b0 -
08
b1010 "
b1010 ,
1A
00
05
0:
0?
0/
14
b0 &
b0 (
b0 +
b1010 #
b1010 )
b1010 %
b1010 '
b1010 *
b1010 B
b0 C
#16100000
b1011 "
b1011 ,
12
10
b1011 #
b1011 )
b1 &
b1 (
b1 +
b1 C
#16200000
1<
1;
b10 $
b10 -
13
02
b1100 "
b1100 ,
07
00
15
b1100 #
b1100 )
b10 &
b10 (
b10 +
b10 C
#16300000
b1101 "
b1101 ,
12
10
b1101 #
b1101 )
b11 &
b11 (
b11 +
b11 C
#16400000
0=
0;
1A
03
0@
02
17
b1110 "
b1110 ,
1<
b0 $
b0 -
08
00
05
1:
b1110 #
b1110 )
b100 &
b100 (
b100 +
b100 C
#16500000
b1111 "
b1111 ,
12
10
b1111 #
b1111 )
b101 &
b101 (
b101 +
b101 C
#16600000
1=
0A
1@
18
0<
1;
b1110 $
b1110 -
13
02
b0 "
b0 ,
07
00
15
b0 #
b0 )
b110 &
b110 (
b110 +
b110 C
#16700000
b1 "
b1 ,
12
10
b1 #
b1 )
b111 &
b111 (
b111 +
b111 C
#16800000
0;
1!
03
0@
02
17
0<
b1000 $
b1000 -
08
b10 "
b10 ,
0A
00
05
0:
1?
b10 #
b10 )
b1000 &
b1000 (
b1000 +
b1000 C
#16900000
b11 "
b11 ,
12
10
b11 #
b11 )
b1001 &
b1001 (
b1001 +
b1001 C
#17000000
1<
1;
b1010 $
b1010 -
13
02
b100 "
b100 ,
07
00
15
b100 #
b100 )
b1010 &
b1010 (
b1010 +
b1010 C
#17100000
b101 "
b101 ,
12
10
b101 #
b101 )
b1011 &
b1011 (
b1011 +
b1011 C
#17200000
0;
0A
03
0@
02
17
b110 "
b110 ,
1<
b1000 $
b1000 -
08
00
05
1:
b110 #
b110 )
b1100 &
b1100 (
b1100 +
b1100 C
#17300000
b111 "
b111 ,
12
10
b111 #
b111 )
b1101 &
b1101 (
b1101 +
b1101 C
