A3/day3/example.v
`timescale 1ns / 1ps

module example (
    input wire inA,
    input wire clk,
    output wire out1,
    output wire out2
);

    reg out1_reg, out2_reg;


    always @(posedge clk) begin
        out1_reg <= inA;
    end

    always @(*) begin
        if (clk==1'b1)
           out2_reg <= inA;
    end

    assign out1 = out1_reg;
    assign out2 = out2_reg;

endmodule

A3/day3/sim_example.v
module sim_example;

    parameter HALF_CYCLE = 30;

    reg inA, clk;
    wire out1, out2;

    example example_mod(inA, clk, out1, out2);

    always begin
        clk = 1'b1;
        #(HALF_CYCLE) clk = 1'b0;
        #(HALF_CYCLE);
    end

    initial begin
      $dumpfile("sim_example.vcd");
      $dumpvars(0, example_mod);

      inA <= 1'b0;
      #100;
      inA <= 1'b1;
      #100;
      inA <= 1'b0;
      #100;
      inA <= 1'b1;
      #100;

      $finish;
    end

endmodule

A3/day3/sim_example.vcd
$date
	Sat May  4 16:33:14 2024
$end
$version
	Icarus Verilog
$end
$timescale
	1ps
$end
$scope module sim_example $end
$scope module example_mod $end
$var wire 1 ! clk $end
$var wire 1 " inA $end
$var wire 1 # out1 $end
$var wire 1 $ out2 $end
$var reg 1 % out1_reg $end
$var reg 1 & out2_reg $end
$upscope $end
$upscope $end
$enddefinitions $end
#0
$dumpvars
0&
x%
0$
x#
0"
1!
$end
#30000
0!
#60000
0#
0%
1!
#90000
0!
#100000
1"
#120000
1$
1&
1#
1%
1!
#150000
0!
#180000
1!
#200000
0$
0&
0"
#210000
0!
#240000
0#
0%
1!
#270000
0!
#300000
1$
1&
1"
1!
#330000
0!
#360000
1#
1%
1!
