A3/day3/counter2.v
`timescale 1ns / 1ps

module counter2 (
  input wire start,
  input wire rst,
  input wire clk,
  output wire out
);

  reg out_reg;
  integer cnt = -1;

  always @(posedge clk) begin
    if (start == 1'b1)
      cnt = 0;
    if (cnt > -1) begin
      if (cnt == 0)
        out_reg <= 1'b1;
      else
        out_reg <= 1'b0;
    cnt = (cnt + 1) % 4;
    end
  end

  always @(posedge rst) begin
    cnt = 0;
  end

  assign out = out_reg;

endmodule

A3/day3/sim_counter2.v
module sim_counter2;

    parameter HALF_CYCLE = 10;

    reg start, rst, clk;
    wire out;

    counter2 counter2_mod(start, rst, clk, out);

    always begin
        clk = 1'b1;
        #(HALF_CYCLE) clk = 1'b0;
        #(HALF_CYCLE);
    end

    initial begin
      $dumpfile("sim_counter2.vcd");
      $dumpvars(0, counter2_mod);

      start <= 1'b0;
      #15;
      start <= 1'b1;
      #10;
      start <= 1'b0;
      #50;
      rst <= 1'b1;
      #10;
      rst <= 1'b0;
      #30;
      rst <= 1'b1;
      #10;
      rst <= 1'b0;
      #30;
      start <= 1'b1;
      #10;
      start <= 1'b0;
      #130;

      $finish;
    end

endmodule

A3/day3/sim_counter2.vcd
$date
	Sat May  4 17:02:20 2024
$end
$version
	Icarus Verilog
$end
$timescale
	1ps
$end
$scope module sim_counter2 $end
$scope module counter2_mod $end
$var wire 1 ! clk $end
$var wire 1 " out $end
$var wire 1 # rst $end
$var wire 1 $ start $end
$var reg 1 % out_reg $end
$var integer 32 & cnt [31:0] $end
$upscope $end
$upscope $end
$enddefinitions $end
#0
$dumpvars
b11111111111111111111111111111111 &
x%
0$
x#
x"
1!
$end
#10000
0!
#15000
1$
#20000
1"
1%
b1 &
1!
#25000
0$
#30000
0!
#40000
0"
0%
b10 &
1!
#50000
0!
#60000
b11 &
1!
#70000
0!
#75000
b0 &
1#
#80000
1"
1%
b1 &
1!
#85000
0#
#90000
0!
#100000
0"
0%
b10 &
1!
#110000
0!
#115000
b0 &
1#
#120000
1"
1%
b1 &
1!
#125000
0#
#130000
0!
#140000
0"
0%
b10 &
1!
#150000
0!
#155000
1$
#160000
1"
1%
b1 &
1!
#165000
0$
#170000
0!
#180000
0"
0%
b10 &
1!
#190000
0!
#200000
b11 &
1!
#210000
0!
#220000
b0 &
1!
#230000
0!
#240000
1"
1%
b1 &
1!
#250000
0!
#260000
0"
0%
b10 &
1!
#270000
0!
#280000
b11 &
1!
