A3/day3/counter.v
`timescale 1ns / 1ps

module counter (
  input wire start,
  input wire clk,
  output wire out
);

  reg out_reg;
  integer cnt = -1;

  always @(posedge clk) begin
    if (start == 1'b1)
      cnt = 0;
    if (cnt > -1) begin
      if (cnt == 0)
        out_reg <= 1'b1;
      else
        out_reg <= 1'b0;
    cnt = (cnt + 1) % 4;
    end
  end

  assign out = out_reg;

endmodule

A3/day3/sim_counter.v
module sim_counter;

    parameter HALF_CYCLE = 10;

    reg start, clk;
    wire out;

    counter counter_mod(start, clk, out);

    always begin
        clk = 1'b1;
        #(HALF_CYCLE) clk = 1'b0;
        #(HALF_CYCLE);
    end

    initial begin
      $dumpfile("sim_counter.vcd");
      $dumpvars(0, counter_mod);

      start <= 1'b0;
      #15;
      start <= 1'b1;
      #10;
      start <= 1'b0;
      #130;
      start <= 1'b1;
      #10;
      start <= 1'b0;
      #130;

      // #70;
      // start <= 1'b1;
      // #20;
      // start <= 1'b0;

      $finish;
    end

endmodule

A3/day3/sim_counter.vcd
$date
	Mon Apr 22 15:28:27 2024
$end
$version
	Icarus Verilog
$end
$timescale
	1ps
$end
$scope module sim_counter $end
$scope module counter_mod $end
$var wire 1 ! clk $end
$var wire 1 " out $end
$var wire 1 # start $end
$var reg 1 $ out_reg $end
$var integer 32 % cnt [31:0] $end
$upscope $end
$upscope $end
$enddefinitions $end
#0
$dumpvars
b11111111111111111111111111111111 %
x$
0#
x"
1!
$end
#10000
0!
#15000
1#
#20000
1"
1$
b1 %
1!
#25000
0#
#30000
0!
#40000
0"
0$
b10 %
1!
#50000
0!
#60000
b11 %
1!
#70000
0!
#80000
b0 %
1!
#90000
0!
#100000
1"
1$
b1 %
1!
#110000
0!
#120000
0"
0$
b10 %
1!
#130000
0!
#140000
b11 %
1!
#150000
0!
#155000
1#
#160000
1"
1$
b1 %
1!
#165000
0#
#170000
0!
#180000
0"
0$
b10 %
1!
#190000
0!
#200000
b11 %
1!
#210000
0!
#220000
b0 %
1!
#230000
0!
#240000
1"
1$
b1 %
1!
#250000
0!
#260000
0"
0$
b10 %
1!
#270000
0!
#280000
b11 %
1!
